sunfluidhbox/__init__.py
sunfluidhbox/box.py
sunfluidhbox/embed.py
sunfluidhbox/pipecom.py
sunfluidhbox/processcom.py
sunfluidhbox-0.2.0.dist-info/DESCRIPTION.rst
sunfluidhbox-0.2.0.dist-info/METADATA
sunfluidhbox-0.2.0.dist-info/RECORD
sunfluidhbox-0.2.0.dist-info/WHEEL
sunfluidhbox-0.2.0.dist-info/metadata.json
sunfluidhbox-0.2.0.dist-info/top_level.txt
